calculator/test_peripherals/rtl/cores/test/mult_z/state_machinemult.v
module state_machinemult(
input clk,
input rst,
input init,
input c,
input b0,

output reg acc,
output reg ld,
output reg sh,
output reg done);//done


parameter START= 3'b000;
parameter CHECK0= 3'b001;
parameter ACUMU= 3'b010;
parameter SHIFT = 3'b011;
parameter CHECK1= 3'b100;
parameter END= 3'b101;


reg[2:0]state;

initial begin 
    ld = 0;
    sh = 0;
    acc = 0;
    done = 0; 
end
reg [4:0] counter;

always @(posedge clk)
begin

    if(rst)
        state <= START;
    else
    begin
        case(state)
            START:
            begin
                if(init) begin
                    counter <= 0;
                    state = CHECK0;
                end else
                    state = START;
            end

            CHECK0:
            begin
                if(b0)
                    state = ACUMU;
                else
                    state = SHIFT;
            end

            ACUMU:
                state = SHIFT;

            SHIFT:
                state = CHECK1;
            
            CHECK1:
                if(c)
                    state = END;
                else
                    state = CHECK0;

            END: begin
                counter <= counter + 1;
                if (counter == 28)
                    state = START;
                else
                    state = END;
            end 
            default:
                state = START;

        endcase
    end
end

always @(state) begin
    case(state)
        START:begin
            ld = 1;
            sh = 0;
            acc = 0;
            done = 0; 
        end
        CHECK0:begin
            ld = 0;
            sh = 0;
            acc = 0;
            done = 0;
        end
        ACUMU:begin
            ld = 0;
            sh = 0;
            acc = 1;
            done = 0;
        end
        SHIFT:begin
            ld = 0;
            sh = 1;
            acc = 0;
            done = 0;
        end
        CHECK1:begin
            ld = 0;
            sh = 0;
            acc = 0;
            done = 0;
        end
        END:begin
            ld = 0;
            sh = 0;
            acc = 0;
            done = 1;
        end
        default:begin
            ld = 1;
            sh = 0;
            acc = 0;
            done = 0; 
        end
    endcase
end



`ifdef BENCH
reg [8*40:1] state_name;
always @(*) begin
    case(state)
        START    : state_name = "START";
        CHECK0    : state_name = "CHECK0";
        CHECK1    : state_name = "CHECK1";
        SHIFT    : state_name = "SHIFT";
        ACUMU     : state_name = "ACUMU";
        END      : state_name = "END";
    endcase
end
`endif


endmodule

calculator/cores/mult/acc.v
module acc (
input clk,
input acc,
input reset,
input [15:0]A,
output reg[31:0]R
);  

initial R = 0;

always @(negedge clk)
    begin
        if (reset) R <= 32'b0;
        else if (acc) R <= R + {16'b0,A};
    end 

endmodule

calculator/test_peripherals/rtl/cores/test/mult_z/mult/comp.v
module comp (
input [15:0]B,
output c);

assign c = (B == 16'b0);

endmodule

calculator/cores/mult/regB.v
module regB (
input clk,
input load,
input shift,
input [15:0]B,
output reg[15:0]Bout);

always @(negedge clk)
begin
    if (load) Bout <= B;
    else if (shift) Bout <= Bout>>1; 

end

endmodule

calculator/cores/mult/regA.v
module regA (
    input clk,
    input load,
    input shift,
    input [15:0] A,
    output reg [31:0] Aout
);

initial Aout = 32'b0;


always @(negedge clk)
begin
    if (load)
        Aout <= {16'b0, A};
    else if (shift)
        Aout <= Aout << 1;
end

endmodule

calculator/cores/mult/mult.v
module mult(clk, rst, init, A, B, R, done);
input clk;
input rst;
input init;
input [15:0]A;
input [15:0]B;

output [31:0]R;
output done;


wire w_c;
wire w_ld;
wire w_sh;
wire w_acc;


wire [15:0]w_a; //Este es el que le entra al modulo reg A
wire [15:0]w_b; //Este es el que le sale al modulo reg A


regA regA0(.clk(clk),.load(w_ld),.shift(w_sh),.A(A),.Aout(w_a));//done  

regB regB0(.clk(clk),.load(w_ld),.shift(w_sh),.B(B),.Bout(w_b)); //doneee

comp comp0(.B(w_b),.c(w_c));//donee


acc acc0(.clk(clk),.acc(w_acc),.reset(w_ld),.A(w_a),.R(R));//done  


state_machinemult state_machinemult0(.clk(clk),.rst(rst),.init(init),.c(w_c),.b0(w_b[0]),.acc(w_acc),.ld(w_ld),.sh(w_sh),.done(done));//done

endmodule

calculator/test_peripherals/rtl/cores/test/mult_z/mult_TB.v
`timescale 1ns / 1ns
`define SIMULATION

module mult_TB;

    reg clk;
    reg rst;
    reg start;

    reg [15:0] in_A;
    reg [15:0] in_B;

    wire [31:0] w_R;
    wire done;

    mult uut (
        .clk(clk),
        .rst(rst),
        .init(start),
        .A(in_A),
        .B(in_B),
        .R(w_R),
        .done(done)
    );

    parameter PERIOD = 20;
    parameter real DUTY_CYCLE = 0.5;
    parameter OFFSET = 0;

    reg [20:0] i;

    event reset_trigger;
    event reset_done_trigger;

    // Reset logic
    initial begin
        forever begin

            @(reset_trigger);
            @(negedge clk);

            rst = 1;

            @(negedge clk);

            rst = 0;

            -> reset_done_trigger;

        end
    end

    // Initialize inputs
    initial begin

        clk   = 0;
        rst   = 1;
        start = 0;

        in_A  = 16'd9;
        in_B  = 16'd3;

    end

    // Clock generation
    initial begin

        #OFFSET;

        forever begin

            clk = 1'b0;
            #(PERIOD - (PERIOD * DUTY_CYCLE));

            clk = 1'b1;
            #(PERIOD * DUTY_CYCLE);

        end
    end

    // Stimulos
    initial begin

        // Trigger reset
        #10 -> reset_trigger;

        @(reset_done_trigger);
        @(posedge clk);

        start = 0;

        @(posedge clk);

        start = 1;

        for(i = 0; i < 2; i = i + 1) begin
            @(posedge clk);
        end

        start = 0;

        for(i = 0; i < 17; i = i + 1) begin
            @(posedge clk);
        end

    end

    // Dump waves
    initial begin : TEST_CASE

        $dumpfile("mult_TB.vcd");
        $dumpvars(-1, uut);

        #((PERIOD * DUTY_CYCLE) * 120) $finish;

    end

endmodule

cores/mult/mult_TB.vcd
$date
	Thu Jun  4 07:16:18 2026
$end
$version
	Icarus Verilog
$end
$timescale
	1ns
$end
$scope module mult_TB $end
$scope module uut $end
$var wire 16 ! A [15:0] $end
$var wire 16 " B [15:0] $end
$var wire 1 # clk $end
$var wire 1 $ init $end
$var wire 1 % rst $end
$var wire 1 & w_sh $end
$var wire 1 ' w_ld $end
$var wire 1 ( w_c $end
$var wire 16 ) w_b [15:0] $end
$var wire 1 * w_acc $end
$var wire 16 + w_a [15:0] $end
$var wire 1 , done $end
$var wire 32 - R [31:0] $end
$scope module acc0 $end
$var wire 16 . A [15:0] $end
$var wire 1 # clk $end
$var wire 1 ' reset $end
$var wire 1 * acc $end
$var reg 32 / R [31:0] $end
$upscope $end
$scope module comp0 $end
$var wire 1 ( c $end
$var wire 16 0 B [15:0] $end
$upscope $end
$scope module regA0 $end
$var wire 16 1 A [15:0] $end
$var wire 1 # clk $end
$var wire 1 & shift $end
$var wire 1 ' load $end
$var reg 32 2 Aout [31:0] $end
$upscope $end
$scope module regB0 $end
$var wire 16 3 B [15:0] $end
$var wire 1 # clk $end
$var wire 1 & shift $end
$var wire 1 ' load $end
$var reg 16 4 Bout [15:0] $end
$upscope $end
$scope module state_machinemult0 $end
$var wire 1 5 b0 $end
$var wire 1 ( c $end
$var wire 1 # clk $end
$var wire 1 $ init $end
$var wire 1 % rst $end
$var parameter 3 6 ACUMU $end
$var parameter 3 7 CHECK0 $end
$var parameter 3 8 CHECK1 $end
$var parameter 3 9 END $end
$var parameter 3 : SHIFT $end
$var parameter 3 ; START $end
$var reg 1 * acc $end
$var reg 5 < counter [4:0] $end
$var reg 1 , done $end
$var reg 1 ' ld $end
$var reg 1 & sh $end
$var reg 3 = state [2:0] $end
$var reg 320 > state_name [320:1] $end
$upscope $end
$upscope $end
$upscope $end
$enddefinitions $end
$comment Show the parameter values. $end
$dumpall
b0 ;
b11 :
b101 9
b100 8
b1 7
b10 6
$end
#0
$dumpvars
bx >
bx =
bx <
x5
bx 4
b11 3
b0 2
b1001 1
bx 0
b0 /
b0 .
b0 -
0,
b0 +
0*
bx )
x(
0'
0&
1%
0$
0#
b11 "
b1001 !
$end
#10
b101001101010100010000010101001001010100 >
1'
b0 =
1#
#20
15
b1001 +
b1001 .
0(
b11 )
b11 0
b11 4
b1001 2
0#
#30
1#
#40
0%
0#
#50
1#
#60
0#
#70
1$
1#
#80
0#
#90
b0 <
0'
b10000110100100001000101010000110100101100110000 >
b1 =
1#
#100
0#
#110
b100000101000011010101010100110101010101 >
1*
0$
b10 =
1#
#120
b1001 -
b1001 /
0#
#130
0*
1&
b101001101001000010010010100011001010100 >
b11 =
1#
#140
b10010 +
b10010 .
b1 )
b1 0
b1 4
b10010 2
0#
#150
b10000110100100001000101010000110100101100110001 >
0&
b100 =
1#
#160
0#
#170
b10000110100100001000101010000110100101100110000 >
b1 =
1#
#180
0#
#190
b100000101000011010101010100110101010101 >
1*
b10 =
1#
#200
b11011 -
b11011 /
0#
#210
0*
1&
b101001101001000010010010100011001010100 >
b11 =
1#
#220
05
b100100 +
b100100 .
1(
b0 )
b0 0
b0 4
b100100 2
0#
#230
b10000110100100001000101010000110100101100110001 >
0&
b100 =
1#
#240
0#
#250
1,
b10001010100111001000100 >
b101 =
1#
#260
0#
#270
b1 <
1#
#280
0#
#290
b10 <
1#
#300
0#
#310
b11 <
1#
#320
0#
#330
b100 <
1#
#340
0#
#350
b101 <
1#
#360
0#
#370
b110 <
1#
#380
0#
#390
b111 <
1#
#400
0#
#410
b1000 <
1#
#420
0#
#430
b1001 <
1#
#440
0#
#450
b1010 <
1#
#460
0#
#470
b1011 <
1#
#480
0#
#490
b1100 <
1#
#500
0#
#510
b1101 <
1#
#520
0#
#530
b1110 <
1#
#540
0#
#550
b1111 <
1#
#560
0#
#570
b10000 <
1#
#580
0#
#590
b10001 <
1#
#600
0#
#610
b10010 <
1#
#620
0#
#630
b10011 <
1#
#640
0#
#650
b10100 <
1#
#660
0#
#670
b10101 <
1#
#680
0#
#690
b10110 <
1#
#700
0#
#710
b10111 <
1#
#720
0#
#730
b11000 <
1#
#740
0#
#750
b11001 <
1#
#760
0#
#770
b11010 <
1#
#780
0#
#790
b11011 <
1#
#800
0#
#810
b11100 <
1#
#820
0#
#830
b11101 <
b101001101010100010000010101001001010100 >
0,
1'
b0 =
1#
#840
b1001 +
b1001 .
15
b1001 2
0(
b11 )
b11 0
b11 4
b0 -
b0 /
0#
