calculator/cores/div/state_machinediv.v
module state_machinediv (
input clk,
input rst,
input init,
input ok,
input f,

output reg start,
output reg shiftA,
output reg shiftR,
output reg load,
output reg inc,
output reg done);//done

parameter START       = 3'b111;
parameter SHIFT       = 3'b100;
parameter R_AGG0      = 3'b011;
parameter R_AGG1      = 3'b010;
parameter DECREMENTAR = 3'b001;
parameter END         = 3'b000;


reg [2:0] state;

initial begin 
    start = 0;
    shiftA = 0;
    shiftR = 0;
    load = 0;
    inc = 0;
    done = 0; 
end
reg [4:0] counter;
reg [3:0] counterok;
always @(posedge clk)
begin

    if(rst)
        state <= START;
    else
    begin
        case(state)
            START:
            begin
                if(init)begin
                    counter <= 0;
                    //counterok <= 0;
                    state = SHIFT;
                    end
                else
                    state = START;
            end

            SHIFT:
            begin
                if(ok)
                    state = R_AGG1;
                else
                    state = R_AGG0;
            end

            R_AGG1: begin
                state = DECREMENTAR;
            end
            R_AGG0: begin
                state = DECREMENTAR;
            end
            DECREMENTAR:
            begin
                if(f)
                    state = END;
                else
                    state = SHIFT;
            end

            END: begin
                counter <= counter + 1;
                if (counter == 28)
                    state = START;
                else
                    state = END;
            end 
            default:
                state = START;
        endcase
    end
end

always @(state) begin
    case(state)
        START:begin
            start = 1;
            shiftA = 0;
            shiftR = 0;
            load = 0;
            inc = 0;
            done = 0;
        end
        SHIFT:begin
            start = 0;
            shiftA = 1;
            shiftR = 0;
            load = 0;
            inc = 0;
            done = 0;
        end
            R_AGG0:begin
            start = 0;
            shiftA = 0;
            shiftR = 1;
            load = 0;
            inc = 0;
            done = 0;
        end
            R_AGG1:begin
            start = 0;
            shiftA = 0;
            shiftR = 0;
            load = 1;
            inc = 0;
            done = 0;
        end
            DECREMENTAR:begin
            start = 0;
            shiftA = 0;
            shiftR = 0;
            load = 0;
            inc = 1;
            done = 0;
        end
            END:begin
            start = 0;
            shiftA = 0;
            shiftR = 0;
            load = 0;
            inc = 0;
            done = 1;
        end
        default:begin
            start = 1;
            shiftA = 0;
            shiftR = 0;
            load = 0;
            inc = 0;
            done = 0;
        end
    endcase
end

`ifdef BENCH
reg [8*40:1] state_name;
always @(*) begin
    case(state)
        START       : state_name = "START";
        R_AGG0      : state_name = "R_AGG0";
        R_AGG1      : state_name = "R_AGG1";
        SHIFT       : state_name = "SHIFT";
        DECREMENTAR : state_name = "DECREMENTAR";
        END         : state_name = "END";
    endcase
end
`endif

endmodule

test_peripherals/rtl/cores/test/div/comp2.v
module comp2 (
input [4:0]count,
output f);//done

assign f = (count == 0);

endmodule

cores/div/increaser.v
module increaser (
    input clk,
    input inc,
    input reset,

    output reg [4:0] count
);

always @(negedge clk)
begin

    if(reset)
        count <= 5'd16;

    else if(inc)
        count <= count - 1;

end

endmodule

calculator/cores/div/regr.v
module regr (
    input clk,
    input rst,
    input shiftR,
    input add,

    output reg [15:0] R
);

initial R = 16'b0;

always @(negedge clk)
begin
    if (rst)
        R <= 16'b0;
    else if(add)
        R <= (R << 1) + 1;
    else if(shiftR)
        R <= R << 1;
end

endmodule


//do

calculator/cores/div/sumac2.v
module sumac2(
input [15:0]Aprima,
input [15:0]B,
output [15:0]Aprimain); 

assign Aprimain = Aprima - B;
endmodule

calculator/test_peripherals/rtl/cores/test/div/comp.v
module comp (
input [15:0]Aprima,
input [15:0]B,
output ok);


assign ok = (Aprima >= B);

endmodule
// si A' es mayot que B entonces ok = 1
/* 
module comp(
input [15:0]Aprima,
input [15:0]B,
output ok);
reg tmp;
initial tmp = 0;
assign ok = tmp;
always@(*)
tmp = (Aprima>B) ? 1'b1 : 1'b0;
endmodule
*/

cores/div/regB.v
module regB (
input clk,
input load,
input [15:0]B,
output reg[15:0]Bout
); 

always @(negedge clk)
begin
    if(load) Bout <= B ;
end
endmodule

cores/div/regA.v
module regA (
    input clk,
    input load,
    input load1,
    input shiftA,
    input [15:0] A,
    input [15:0] inAprima,

    output [15:0] Aout
);

reg [31:0] regA_total;

assign Aout = regA_total[31:16];

always @(negedge clk)
begin
    if (load)
        regA_total <= {16'b0,A};
    else if (load1)
        regA_total[31:16] <= inAprima;
    else if (shiftA)
        regA_total <= regA_total << 1;
end

endmodule

calculator/cores/div/div.v
module div(clk, rst, init, A, B, R, done);
input clk;
input rst;
input init;
input [15:0]A;
input [15:0]B;

output [15:0]R;
output done;

wire w_start;
wire w_shiftA;
wire w_shiftR;
wire w_load;
wire w_inc;
wire w_ok;
wire w_f;

wire [15:0]w_Aprimain; //Este es el que le entra al modulo reg A
wire [15:0]w_Aprimaout; //Este es el que le sale al modulo reg A
wire [15:0]w_B;
wire [4:0]w_count;

regA regA0(.clk(clk),.load(w_start),.load1(w_load),.shiftA(w_shiftA),.A(A),.inAprima(w_Aprimain),.Aout(w_Aprimaout));//done  

regB regB0(.clk(clk),.load(w_start),.B(B),.Bout(w_B)); //doneee

comp comp0(.Aprima(w_Aprimaout),.B(w_B),.ok(w_ok));//donee

sumac2 sumac20(.Aprima(w_Aprimaout),.B(w_B),.Aprimain(w_Aprimain)); //done

regr regr0(.clk(clk),.rst(rst),.shiftR(w_shiftR),.add(w_load),.R(R));//done

increaser increaser0(.clk(clk),.inc(w_inc),.reset(w_start),.count(w_count));//done


comp2 comp20(.count(w_count),.f(w_f));//done


state_machinediv state_machinediv0(.clk(clk),.rst(rst),.init(init),.ok(w_ok),.f(w_f),.start(w_start),.shiftA(w_shiftA),.shiftR(w_shiftR),.load(w_load),.inc(w_inc),.done(done));//done

endmodule

calculator/test_peripherals/rtl/cores/test/div/div_TB.v
`timescale 1ns / 1ns
`define SIMULATION

module div_TB;

    reg clk;
    reg rst;
    reg start;

    reg [15:0] in_A;
    reg [15:0] in_B;

    wire [15:0] w_R;
    wire done;

    div uut (
        .clk(clk),
        .rst(rst),
        .init(start),
        .A(in_A),
        .B(in_B),
        .R(w_R),
        .done(done)
    );

    parameter PERIOD = 20;
    parameter real DUTY_CYCLE = 0.5;
    parameter OFFSET = 0;

    reg [20:0] i;

    event reset_trigger;
    event reset_done_trigger;

    // Reset logic
    initial begin
        forever begin

            @(reset_trigger);
            @(negedge clk);

            rst = 1;

            @(negedge clk);

            rst = 0;

            -> reset_done_trigger;

        end
    end

    // Initialize inputs
    initial begin

        clk   = 0;
        rst   = 1;
        start = 0;

        in_A  = 16'd1024;
        in_B  = 16'd127;

    end

    // Clock generation
    initial begin

        #OFFSET;

        forever begin

            clk = 1'b0;
            #(PERIOD - (PERIOD * DUTY_CYCLE));

            clk = 1'b1;
            #(PERIOD * DUTY_CYCLE);

        end
    end

    // Stimulos
    initial begin

        // Trigger reset
        #10 -> reset_trigger;

        @(reset_done_trigger);
        @(posedge clk);

        start = 0;

        @(posedge clk);

        start = 1;

        for(i = 0; i < 2; i = i + 1) begin
            @(posedge clk);
        end

        start = 0;

        for(i = 0; i < 17; i = i + 1) begin
            @(posedge clk);
        end

    end

    // Dump waves
    initial begin : TEST_CASE

        $dumpfile("div_TB.vcd");
        $dumpvars(-1, uut);

        #((PERIOD * DUTY_CYCLE) * 120) $finish;

    end

endmodule

cores/div/div_TB.vcd
$date
	Thu Jun  4 08:40:23 2026
$end
$version
	Icarus Verilog
$end
$timescale
	1ns
$end
$scope module div_TB $end
$scope module uut $end
$var wire 16 ! A [15:0] $end
$var wire 16 " B [15:0] $end
$var wire 1 # clk $end
$var wire 1 $ init $end
$var wire 1 % rst $end
$var wire 1 & w_start $end
$var wire 1 ' w_shiftR $end
$var wire 1 ( w_shiftA $end
$var wire 1 ) w_ok $end
$var wire 1 * w_load $end
$var wire 1 + w_inc $end
$var wire 1 , w_f $end
$var wire 5 - w_count [4:0] $end
$var wire 16 . w_B [15:0] $end
$var wire 16 / w_Aprimaout [15:0] $end
$var wire 16 0 w_Aprimain [15:0] $end
$var wire 1 1 done $end
$var wire 16 2 R [15:0] $end
$scope module comp0 $end
$var wire 1 ) ok $end
$var wire 16 3 B [15:0] $end
$var wire 16 4 Aprima [15:0] $end
$upscope $end
$scope module comp20 $end
$var wire 1 , f $end
$var wire 5 5 count [4:0] $end
$upscope $end
$scope module increaser0 $end
$var wire 1 # clk $end
$var wire 1 & reset $end
$var wire 1 + inc $end
$var reg 5 6 count [4:0] $end
$upscope $end
$scope module regA0 $end
$var wire 16 7 A [15:0] $end
$var wire 1 # clk $end
$var wire 1 ( shiftA $end
$var wire 1 * load1 $end
$var wire 1 & load $end
$var wire 16 8 inAprima [15:0] $end
$var wire 16 9 Aout [15:0] $end
$var reg 32 : regA_total [31:0] $end
$upscope $end
$scope module regB0 $end
$var wire 16 ; B [15:0] $end
$var wire 1 # clk $end
$var wire 1 & load $end
$var reg 16 < Bout [15:0] $end
$upscope $end
$scope module regr0 $end
$var wire 1 # clk $end
$var wire 1 % rst $end
$var wire 1 ' shiftR $end
$var wire 1 * add $end
$var reg 16 = R [15:0] $end
$upscope $end
$scope module state_machinediv0 $end
$var wire 1 # clk $end
$var wire 1 , f $end
$var wire 1 $ init $end
$var wire 1 ) ok $end
$var wire 1 % rst $end
$var parameter 3 > DECREMENTAR $end
$var parameter 3 ? END $end
$var parameter 3 @ R_AGG0 $end
$var parameter 3 A R_AGG1 $end
$var parameter 3 B SHIFT $end
$var parameter 3 C START $end
$var reg 5 D counter [4:0] $end
$var reg 1 1 done $end
$var reg 1 + inc $end
$var reg 1 * load $end
$var reg 1 ( shiftA $end
$var reg 1 ' shiftR $end
$var reg 1 & start $end
$var reg 3 E state [2:0] $end
$var reg 320 F state_name [320:1] $end
$upscope $end
$scope module sumac20 $end
$var wire 16 G Aprima [15:0] $end
$var wire 16 H B [15:0] $end
$var wire 16 I Aprimain [15:0] $end
$upscope $end
$upscope $end
$upscope $end
$enddefinitions $end
$comment Show the parameter values. $end
$dumpall
b111 C
b100 B
b10 A
b11 @
b0 ?
b1 >
$end
#0
$dumpvars
bx I
bx H
bx G
bx F
bx E
bx D
b0 =
bx <
b1111111 ;
bx :
bx 9
bx 8
b10000000000 7
bx 6
bx 5
bx 4
bx 3
b0 2
01
bx 0
bx /
bx .
bx -
x,
0+
0*
x)
0(
0'
0&
1%
0$
0#
b1111111 "
b10000000000 !
$end
#10
b101001101010100010000010101001001010100 F
1&
b111 E
1#
#20
b1111111110000001 0
b1111111110000001 8
b1111111110000001 I
0)
b0 /
b0 4
b0 9
b0 G
0,
b10000 -
b10000 5
b10000 6
b1111111 .
b1111111 3
b1111111 <
b1111111 H
b10000000000 :
0#
#30
1#
#40
0%
0#
#50
1#
#60
0#
#70
1$
1#
#80
0#
#90
b0 D
1(
0&
b101001101001000010010010100011001010100 F
b100 E
1#
#100
b100000000000 :
0#
#110
b10100100101111101000001010001110100011100110000 F
1'
0(
0$
b11 E
1#
#120
0#
#130
1+
0'
b100010001000101010000110101001001000101010011010100010101001110010101000100000101010010 F
b1 E
1#
#140
b1111 -
b1111 5
b1111 6
0#
#150
b101001101001000010010010100011001010100 F
0+
1(
b100 E
1#
#160
b1000000000000 :
0#
#170
1'
0(
b10100100101111101000001010001110100011100110000 F
b11 E
1#
#180
0#
#190
b100010001000101010000110101001001000101010011010100010101001110010101000100000101010010 F
1+
0'
b1 E
1#
#200
b1110 -
b1110 5
b1110 6
0#
#210
0+
1(
b101001101001000010010010100011001010100 F
b100 E
1#
#220
b10000000000000 :
0#
#230
b10100100101111101000001010001110100011100110000 F
1'
0(
b11 E
1#
#240
0#
#250
1+
0'
b100010001000101010000110101001001000101010011010100010101001110010101000100000101010010 F
b1 E
1#
#260
b1101 -
b1101 5
b1101 6
0#
#270
b101001101001000010010010100011001010100 F
0+
1(
b100 E
1#
#280
b100000000000000 :
0#
#290
1'
0(
b10100100101111101000001010001110100011100110000 F
b11 E
1#
#300
0#
#310
b100010001000101010000110101001001000101010011010100010101001110010101000100000101010010 F
1+
0'
b1 E
1#
#320
b1100 -
b1100 5
b1100 6
0#
#330
0+
1(
b101001101001000010010010100011001010100 F
b100 E
1#
#340
b1000000000000000 :
0#
#350
b10100100101111101000001010001110100011100110000 F
1'
0(
b11 E
1#
#360
0#
#370
1+
0'
b100010001000101010000110101001001000101010011010100010101001110010101000100000101010010 F
b1 E
1#
#380
b1011 -
b1011 5
b1011 6
0#
#390
b101001101001000010010010100011001010100 F
0+
1(
b100 E
1#
#400
b1111111110000010 0
b1111111110000010 8
b1111111110000010 I
b1 /
b1 4
b1 9
b1 G
b10000000000000000 :
0#
#410
1'
0(
b10100100101111101000001010001110100011100110000 F
b11 E
1#
#420
0#
#430
b100010001000101010000110101001001000101010011010100010101001110010101000100000101010010 F
1+
0'
b1 E
1#
#440
b1010 -
b1010 5
b1010 6
0#
#450
0+
1(
b101001101001000010010010100011001010100 F
b100 E
1#
#460
b1111111110000011 0
b1111111110000011 8
b1111111110000011 I
b10 /
b10 4
b10 9
b10 G
b100000000000000000 :
0#
#470
b10100100101111101000001010001110100011100110000 F
1'
0(
b11 E
1#
#480
0#
#490
1+
0'
b100010001000101010000110101001001000101010011010100010101001110010101000100000101010010 F
b1 E
1#
#500
b1001 -
b1001 5
b1001 6
0#
#510
b101001101001000010010010100011001010100 F
0+
1(
b100 E
1#
#520
b1111111110000101 0
b1111111110000101 8
b1111111110000101 I
b100 /
b100 4
b100 9
b100 G
b1000000000000000000 :
0#
#530
1'
0(
b10100100101111101000001010001110100011100110000 F
b11 E
1#
#540
0#
#550
b100010001000101010000110101001001000101010011010100010101001110010101000100000101010010 F
1+
0'
b1 E
1#
#560
b1000 -
b1000 5
b1000 6
0#
#570
0+
1(
b101001101001000010010010100011001010100 F
b100 E
1#
#580
b1111111110001001 0
b1111111110001001 8
b1111111110001001 I
b1000 /
b1000 4
b1000 9
b1000 G
b10000000000000000000 :
0#
#590
b10100100101111101000001010001110100011100110000 F
1'
0(
b11 E
1#
#600
0#
#610
1+
0'
b100010001000101010000110101001001000101010011010100010101001110010101000100000101010010 F
b1 E
1#
#620
b111 -
b111 5
b111 6
0#
#630
b101001101001000010010010100011001010100 F
0+
1(
b100 E
1#
#640
b1111111110010001 0
b1111111110010001 8
b1111111110010001 I
b10000 /
b10000 4
b10000 9
b10000 G
b100000000000000000000 :
0#
#650
1'
0(
b10100100101111101000001010001110100011100110000 F
b11 E
1#
#660
0#
#670
b100010001000101010000110101001001000101010011010100010101001110010101000100000101010010 F
1+
0'
b1 E
1#
#680
b110 -
b110 5
b110 6
0#
#690
0+
1(
b101001101001000010010010100011001010100 F
b100 E
1#
#700
b1111111110100001 0
b1111111110100001 8
b1111111110100001 I
b100000 /
b100000 4
b100000 9
b100000 G
b1000000000000000000000 :
0#
#710
b10100100101111101000001010001110100011100110000 F
1'
0(
b11 E
1#
#720
0#
#730
1+
0'
b100010001000101010000110101001001000101010011010100010101001110010101000100000101010010 F
b1 E
1#
#740
b101 -
b101 5
b101 6
0#
#750
b101001101001000010010010100011001010100 F
0+
1(
b100 E
1#
#760
b1111111111000001 0
b1111111111000001 8
b1111111111000001 I
b1000000 /
b1000000 4
b1000000 9
b1000000 G
b10000000000000000000000 :
0#
#770
1'
0(
b10100100101111101000001010001110100011100110000 F
b11 E
1#
#780
0#
#790
b100010001000101010000110101001001000101010011010100010101001110010101000100000101010010 F
1+
0'
b1 E
1#
#800
b100 -
b100 5
b100 6
0#
#810
0+
1(
b101001101001000010010010100011001010100 F
b100 E
1#
#820
b1 0
b1 8
b1 I
1)
b10000000 /
b10000000 4
b10000000 9
b10000000 G
b100000000000000000000000 :
0#
#830
b10100100101111101000001010001110100011100110001 F
1*
0(
b10 E
1#
#840
b1111111110000010 0
b1111111110000010 8
b1111111110000010 I
0)
b1 /
b1 4
b1 9
b1 G
b10000000000000000 :
b1 2
b1 =
0#
#850
1+
0*
b100010001000101010000110101001001000101010011010100010101001110010101000100000101010010 F
b1 E
1#
#860
b11 -
b11 5
b11 6
0#
#870
b101001101001000010010010100011001010100 F
0+
1(
b100 E
1#
#880
b1111111110000011 0
b1111111110000011 8
b1111111110000011 I
b10 /
b10 4
b10 9
b10 G
b100000000000000000 :
0#
#890
1'
0(
b10100100101111101000001010001110100011100110000 F
b11 E
1#
#900
b10 2
b10 =
0#
#910
b100010001000101010000110101001001000101010011010100010101001110010101000100000101010010 F
1+
0'
b1 E
1#
#920
b10 -
b10 5
b10 6
0#
#930
0+
1(
b101001101001000010010010100011001010100 F
b100 E
1#
#940
b1111111110000101 0
b1111111110000101 8
b1111111110000101 I
b100 /
b100 4
b100 9
b100 G
b1000000000000000000 :
0#
#950
b10100100101111101000001010001110100011100110000 F
1'
0(
b11 E
1#
#960
b100 2
b100 =
0#
#970
1+
0'
b100010001000101010000110101001001000101010011010100010101001110010101000100000101010010 F
b1 E
1#
#980
b1 -
b1 5
b1 6
0#
#990
b101001101001000010010010100011001010100 F
0+
1(
b100 E
1#
#1000
b1111111110001001 0
b1111111110001001 8
b1111111110001001 I
b1000 /
b1000 4
b1000 9
b1000 G
b10000000000000000000 :
0#
#1010
1'
0(
b10100100101111101000001010001110100011100110000 F
b11 E
1#
#1020
b1000 2
b1000 =
0#
#1030
b100010001000101010000110101001001000101010011010100010101001110010101000100000101010010 F
1+
0'
b1 E
1#
#1040
1,
b0 -
b0 5
b0 6
0#
#1050
11
0+
b10001010100111001000100 F
b0 E
1#
#1060
0#
#1070
b1 D
1#
#1080
0#
#1090
b10 D
1#
#1100
0#
#1110
b11 D
1#
#1120
0#
#1130
b100 D
1#
#1140
0#
#1150
b101 D
1#
#1160
0#
#1170
b110 D
1#
#1180
0#
#1190
b111 D
1#
