calculator/test_peripherals/rtl/cores/test/sqrt/state_machinesqrt.v
module state_machinesqrt (
input clk,
input rst,
input init,
input c,
input z,
input m,

output reg ld_A1,
output reg ld_A2,
output reg add_0,
output reg add_1,
output reg ld_R1,
output reg sh,
output reg done);//done




parameter INIT         = 4'b0000;
parameter SHIFT_COUNT  = 4'b0001;
parameter CHECK0       = 4'b0010;
parameter R_1          = 4'b0011;
parameter UPDATE_A     = 4'b0100;
parameter R_SHIFT      = 4'b0101;
parameter CHECK1       = 4'b0110;
parameter R_1_UPDATE_A = 4'b0111;
parameter R_0          = 4'b1000;
parameter CHECK2       = 4'b1001;
parameter END          = 4'b1010;


reg[3:0]state;

initial begin 
    ld_A1 = 0;
    ld_A2 = 0;
    add_0 = 0;
    add_1 = 0;
    ld_R1 = 0;
    sh = 0;
    done = 0;
end
reg [4:0] counter;

always @(posedge clk)
begin

    if(rst)
        state = INIT;
    else
    begin
        case(state)
            INIT:
            begin
                if(init) 
                    begin
                        counter <= 0;
                        state = SHIFT_COUNT;
                    end
                else
                    state = INIT;
            end

            SHIFT_COUNT:
                state = CHECK0;

            CHECK0:
            begin
                if (z) 
                    state = UPDATE_A;
                else
                    state = R_1;
            end
            R_1:
                state = UPDATE_A;
            
            UPDATE_A:
                state = R_SHIFT;
            
            R_SHIFT:
                state = CHECK1;

            CHECK1:
            begin
                if (m) 
                state = R_0;
                else 
                    state = R_1_UPDATE_A;
            end
            R_0:
                state = CHECK2;    
            
            R_1_UPDATE_A:
                state = CHECK2;         
            
            CHECK2:
            begin
                if (c) 
                state = END;
                else 
                    state = R_SHIFT;
            end


            END: begin
                counter <= counter + 1;
                if (counter == 28)
                    state = INIT;
                else
                    state = END;
            end 
            default:
                state = INIT;

        endcase
    end
end

always @(state) begin
    case(state)
        INIT:begin
            ld_A1 = 1;
            ld_A2 = 0;
            add_0 = 0;
            add_1 = 0;
            ld_R1 = 0;
            sh = 0;
            done = 0;
        end
        SHIFT_COUNT:begin
            ld_A1 = 0;
            ld_A2 = 0;
            add_0 = 0;
            add_1 = 0;
            ld_R1 = 0;
            sh = 1;
            done = 0;
        end
        CHECK0:begin
            ld_A1 = 0;
            ld_A2 = 0;
            add_0 = 0;
            add_1 = 0;
            ld_R1 = 0;
            sh = 0;
            done = 0;
        end
        R_1:begin
            ld_A1 = 0;
            ld_A2 = 0;
            add_0 = 0;
            add_1 = 1;
            ld_R1 = 0;
            sh = 0;
            done = 0;
        end
        UPDATE_A:begin
            ld_A1 = 0;
            ld_A2 = 1;
            add_0 = 0;
            add_1 = 0;
            ld_R1 = 0;
            sh = 0;
            done = 0;
        end
        R_SHIFT:begin
            ld_A1 = 0;
            ld_A2 = 0;
            add_0 = 0;
            add_1 = 0;
            ld_R1 = 1;
            sh = 1;
            done = 0;
        end
        CHECK1:begin
            ld_A1 = 0;
            ld_A2 = 0;
            add_0 = 0;
            add_1 = 0;
            ld_R1 = 0;
            sh = 0;
            done = 0;
        end
        R_0:begin
            ld_A1 = 0;
            ld_A2 = 0;
            add_0 = 1;
            add_1 = 0;
            ld_R1 = 0;
            sh = 0;
            done = 0;
        end
        R_1_UPDATE_A:begin
            ld_A1 = 0;
            ld_A2 = 1;
            add_0 = 0;
            add_1 = 1;
            ld_R1 = 0;
            sh = 0;
            done = 0;
        end                
        CHECK2:begin
            ld_A1 = 0;
            ld_A2 = 0;
            add_0 = 0;
            add_1 = 0;
            ld_R1 = 0;
            sh = 0;
            done = 0;
        end
        END:begin
            ld_A1 = 0;
            ld_A2 = 0;
            add_0 = 0;
            add_1 = 0;
            ld_R1 = 0;
            sh = 0;
            done = 1;
        end
        default:begin
            ld_A1 = 0;
            ld_A2 = 0;
            add_0 = 0;
            add_1 = 0;
            ld_R1 = 0;
            sh = 0;
            done = 0;
        end
    endcase
end



`ifdef BENCH
reg [8*40:1] state_name;
always @(*) begin
    case(state)
        INIT        : state_name = "INIT";
        SHIFT_COUNT : state_name = "SHIFT_COUNT";
        CHECK0      : state_name = "CHECK0";
        R_1         : state_name = "R_1";
        UPDATE_A    : state_name = "UPDATE_A";
        R_SHIFT     : state_name = "R_SHIFT";
        CHECK1      : state_name = "CHECK1";
        R_1_UPDATE_A: state_name = "R_1_UPDATE_A";
        R_0         : state_name = "R_0";
        CHECK2      : state_name = "CHECK2";
        END         : state_name = "END";
    endcase
end
`endif


endmodule

test_peripherals/rtl/cores/test/sqrt/comp_count.v
module comp_count(
input [3:0]count, //16 A entonces count es 8 
output reg c);

always @(*)
    if (count == 0)
        c = 1;
    else 
        c = 0;    

endmodule

test_peripherals/rtl/cores/test/sqrt/count.v
module count (
input clk,
input reset,
input dec,
output reg [3:0]count);

always @(negedge clk)
begin
    if(reset)
        count <= 4'd8;
    else if(dec)
        count <= count - 1;
end

endmodule

test_peripherals/rtl/cores/test/sqrt/restar.v
module restar (
input  [9:0]R1,
input  [15:0]A2,
output [15:0]A2out);

assign A2out = (A2 - R1);

endmodule

test_peripherals/rtl/cores/test/sqrt/comp1.v
module comp1 (
input [15:0]A2,
input [9:0]R1,
output m);

assign m = (R1 > A2);

endmodule

test_peripherals/rtl/cores/test/sqrt/regR1.v
module regR1(
input clk,
input rst,
input load,
input [9:0]R01,//({R,2'b01})
output reg [9:0]R1);



always @(negedge clk)
begin
    if (rst)
        R1 <= 10'b0;
    else if (load)
        R1 <= R01;
end
endmodule

calculator/cores/sqrt/regR.v
module regR (
input clk,
input rst,
input add_0,
input add_1,
output reg [7:0] R);

initial R = 8'b0;

always @(negedge clk)
begin
    if (rst)
        R <= 16'b0;
    if (add_0)
        R <= (R<<1);
    else if(add_1)
        R <= (R<<1) + 1;
end
endmodule

cores/sqrt/comp.v
module comp (
input [15:0] A2,
output z);

assign z = (A2 == 16'b0);

endmodule

calculator/test_peripherals/rtl/cores/test/sqrt/regA.v
module regA (
    input clk,
    input load,
    input load2,
    input shift,
    input [15:0] A,
    input [15:0] A2in,

    output [15:0] A2
);


reg [31:0] regA_total;

assign A2 = regA_total[31:16];

always @(negedge clk)
begin
    if (load)
        regA_total <= {16'b0,A};
    else if (load2)
        regA_total[31:16] <= A2in;
    else if (shift)
        regA_total <= regA_total << 2;
end

endmodule

cores/sqrt/sqrt.v
module sqrt(clk, rst, init, A, A2, R, done);
input clk;
input rst;
input init;
input [15:0]A;

output [15:0]A2;
output [7:0]R; //
output done;

wire w_ld_A1;
wire w_ld_A2;
wire w_add_0;
wire w_add_1;
wire w_ld_R1;
wire w_sh;

wire w_c;
wire w_z;
wire w_m;



wire [3:0]w_violeta; //contadorr

wire [15:0]w_A2; //Este es el que le entra al modulo reg A

wire [9:0]w_R1; //Este es el que le sale al modulo r1

regA regA0(.clk(clk),.load(w_ld_A1),.shift(w_sh),.load2(w_ld_A2),.A(A),.A2in(w_A2),.A2(A2));


comp comp0(.A2(A2),.z(w_z));//donee

regR regR0(.clk(clk),.rst(w_ld_A1),.add_0(w_add_0),.add_1(w_add_1),.R(R));//done  

regR1 regR10(.clk(clk),.rst(w_ld_A1),.load(w_ld_R1),.R01({R,2'b01}),.R1(w_R1));

comp1 comp10(.A2(A2),.R1(w_R1),.m(w_m));//donee

restar restar0(.R1(w_R1),.A2(A2),.A2out(w_A2));

count count0(.clk(clk),.reset(w_ld_A1),.dec(w_sh),.count(w_violeta));

comp_count comp_count0(.count(w_violeta),.c(w_c));







state_machinesqrt state_machinesqrt0(.clk(clk),.rst(rst),.init(init),.c(w_c),.z(w_z),.m(w_m),.ld_A1(w_ld_A1),.ld_A2(w_ld_A2),.add_0(w_add_0),.add_1(w_add_1),.ld_R1(w_ld_R1),.sh(w_sh),.done(done));//done

endmodule

calculator/cores/sqrt/sqrt_TB.v
`timescale 1ns / 1ns
`define SIMULATION

module sqrt_TB;

    reg clk;
    reg rst;
    reg start;

    reg [15:0] in_A;

    wire [15:0]w_A2;
    wire [7:0] w_R;
    wire done;

    sqrt uut (
        .clk(clk),
        .rst(rst),
        .init(start),
        .A(in_A),
        .A2(w_A2),
        .R(w_R),
        .done(done)
    );
//module sqrt(clk, rst, init, A, A2, R, done);
    parameter PERIOD = 20;
    parameter real DUTY_CYCLE = 0.5;
    parameter OFFSET = 0;

    reg [20:0] i;

    event reset_trigger;
    event reset_done_trigger;

    // Reset logic
    initial begin
        forever begin

            @(reset_trigger);
            @(negedge clk);

            rst = 1;

            @(negedge clk);

            rst = 0;

            -> reset_done_trigger;

        end
    end

    // Initialize inputs
    initial begin

        clk   = 0;
        rst   = 1;
        start = 0;

        in_A  = 16'd97;

    end

    // Clock generation
    initial begin

        #OFFSET;

        forever begin

            clk = 1'b0;
            #(PERIOD - (PERIOD * DUTY_CYCLE));

            clk = 1'b1;
            #(PERIOD * DUTY_CYCLE);

        end
    end

    // Stimulos
    initial begin

        // Trigger reset
        #10 -> reset_trigger;

        @(reset_done_trigger);
        @(posedge clk);

        start = 0;

        @(posedge clk);

        start = 1;

        for(i = 0; i < 2; i = i + 1) begin
            @(posedge clk);
        end

        start = 0;

        for(i = 0; i < 17; i = i + 1) begin
            @(posedge clk);
        end

    end

    // Dump waves
    initial begin : TEST_CASE

        $dumpfile("sqrt_TB.vcd");
        $dumpvars(-1, uut);

        #((PERIOD * DUTY_CYCLE) * 120) $finish;

    end

endmodule

test_peripherals/rtl/cores/test/sqrt/sqrt_TB.vcd
$date
	Sat Jun  6 23:56:38 2026
$end
$version
	Icarus Verilog
$end
$timescale
	1ns
$end
$scope module sqrt_TB $end
$scope module uut $end
$var wire 16 ! A [15:0] $end
$var wire 1 " clk $end
$var wire 1 # init $end
$var wire 1 $ rst $end
$var wire 1 % w_z $end
$var wire 4 & w_violeta [3:0] $end
$var wire 1 ' w_sh $end
$var wire 1 ( w_m $end
$var wire 1 ) w_ld_R1 $end
$var wire 1 * w_ld_A2 $end
$var wire 1 + w_ld_A1 $end
$var wire 1 , w_c $end
$var wire 1 - w_add_1 $end
$var wire 1 . w_add_0 $end
$var wire 10 / w_R1 [9:0] $end
$var wire 16 0 w_A2 [15:0] $end
$var wire 1 1 done $end
$var wire 8 2 R [7:0] $end
$var wire 16 3 A2 [15:0] $end
$scope module comp0 $end
$var wire 1 % z $end
$var wire 16 4 A2 [15:0] $end
$upscope $end
$scope module comp10 $end
$var wire 1 ( m $end
$var wire 10 5 R1 [9:0] $end
$var wire 16 6 A2 [15:0] $end
$upscope $end
$scope module comp_count0 $end
$var wire 4 7 count [3:0] $end
$var reg 1 , c $end
$upscope $end
$scope module count0 $end
$var wire 1 " clk $end
$var wire 1 + reset $end
$var wire 1 ' dec $end
$var reg 4 8 count [3:0] $end
$upscope $end
$scope module regA0 $end
$var wire 16 9 A [15:0] $end
$var wire 1 " clk $end
$var wire 1 ' shift $end
$var wire 1 * load2 $end
$var wire 1 + load $end
$var wire 16 : A2in [15:0] $end
$var wire 16 ; A2 [15:0] $end
$var reg 32 < regA_total [31:0] $end
$upscope $end
$scope module regR0 $end
$var wire 1 " clk $end
$var wire 1 + rst $end
$var wire 1 - add_1 $end
$var wire 1 . add_0 $end
$var reg 8 = R [7:0] $end
$upscope $end
$scope module regR10 $end
$var wire 10 > R01 [9:0] $end
$var wire 1 " clk $end
$var wire 1 + rst $end
$var wire 1 ) load $end
$var reg 10 ? R1 [9:0] $end
$upscope $end
$scope module restar0 $end
$var wire 16 @ A2 [15:0] $end
$var wire 10 A R1 [9:0] $end
$var wire 16 B A2out [15:0] $end
$upscope $end
$scope module state_machinesqrt0 $end
$var wire 1 , c $end
$var wire 1 " clk $end
$var wire 1 # init $end
$var wire 1 ( m $end
$var wire 1 $ rst $end
$var wire 1 % z $end
$var parameter 4 C CHECK0 $end
$var parameter 4 D CHECK1 $end
$var parameter 4 E CHECK2 $end
$var parameter 4 F END $end
$var parameter 4 G INIT $end
$var parameter 4 H R_0 $end
$var parameter 4 I R_1 $end
$var parameter 4 J R_1_UPDATE_A $end
$var parameter 4 K R_SHIFT $end
$var parameter 4 L SHIFT_COUNT $end
$var parameter 4 M UPDATE_A $end
$var reg 1 . add_0 $end
$var reg 1 - add_1 $end
$var reg 5 N counter [4:0] $end
$var reg 1 1 done $end
$var reg 1 + ld_A1 $end
$var reg 1 * ld_A2 $end
$var reg 1 ) ld_R1 $end
$var reg 1 ' sh $end
$var reg 4 O state [3:0] $end
$var reg 320 P state_name [320:1] $end
$upscope $end
$upscope $end
$upscope $end
$enddefinitions $end
$comment Show the parameter values. $end
$dumpall
b100 M
b1 L
b101 K
b111 J
b11 I
b1000 H
b0 G
b1010 F
b1001 E
b110 D
b10 C
$end
#0
$dumpvars
bx P
bx O
bx N
bx B
bx A
bx @
bx ?
b1 >
b0 =
bx <
bx ;
bx :
b1100001 9
bx 8
bx 7
bx 6
bx 5
bx 4
bx 3
b0 2
01
bx 0
bx /
0.
0-
x,
0+
0*
0)
x(
0'
bx &
x%
1$
0#
0"
b1100001 !
$end
#10
b1001001010011100100100101010100 P
1+
b0 O
1"
#20
0,
b0 0
b0 :
b0 B
0(
1%
b0 3
b0 4
b0 6
b0 ;
b0 @
b1000 &
b1000 7
b1000 8
b0 /
b0 5
b0 ?
b0 A
b1100001 <
0"
#30
1"
#40
0$
0"
#50
1"
#60
0"
#70
1#
1"
#80
0"
#90
b0 N
1'
0+
b101001101001000010010010100011001010100010111110100001101001111010101010100111001010100 P
b1 O
1"
#100
b111 &
b111 7
b111 8
b110000100 <
0"
#110
b10000110100100001000101010000110100101100110000 P
0'
0#
b10 O
1"
#120
0"
#130
1*
b101010101010000010001000100000101010100010001010101111101000001 P
b100 O
1"
#140
0"
#150
b1010010010111110101001101001000010010010100011001010100 P
1'
1)
0*
b101 O
1"
#160
b11000010000 <
b1111111111111111 0
b1111111111111111 :
b1111111111111111 B
1(
b1 /
b1 5
b1 ?
b1 A
b110 &
b110 7
b110 8
0"
#170
0'
0)
b10000110100100001000101010000110100101100110001 P
b110 O
1"
#180
0"
#190
b10100100101111100110000 P
1.
b1000 O
1"
#200
0"
#210
0.
b10000110100100001000101010000110100101100110010 P
b1001 O
1"
#220
0"
#230
b1010010010111110101001101001000010010010100011001010100 P
1'
1)
b101 O
1"
#240
b1100001000000 <
b101 &
b101 7
b101 8
0"
#250
0'
0)
b10000110100100001000101010000110100101100110001 P
b110 O
1"
#260
0"
#270
b10100100101111100110000 P
1.
b1000 O
1"
#280
0"
#290
0.
b10000110100100001000101010000110100101100110010 P
b1001 O
1"
#300
0"
#310
b1010010010111110101001101001000010010010100011001010100 P
1'
1)
b101 O
1"
#320
b110000100000000 <
b100 &
b100 7
b100 8
0"
#330
0'
0)
b10000110100100001000101010000110100101100110001 P
b110 O
1"
#340
0"
#350
b10100100101111100110000 P
1.
b1000 O
1"
#360
0"
#370
0.
b10000110100100001000101010000110100101100110010 P
b1001 O
1"
#380
0"
#390
b1010010010111110101001101001000010010010100011001010100 P
1'
1)
b101 O
1"
#400
b0 0
b0 :
b0 B
0(
0%
b1 3
b1 4
b1 6
b1 ;
b1 @
b11000010000000000 <
b11 &
b11 7
b11 8
0"
#410
0'
0)
b10000110100100001000101010000110100101100110001 P
b110 O
1"
#420
0"
#430
b10100100101111100110001010111110101010101010000010001000100000101010100010001010101111101000001 P
1-
1*
b111 O
1"
#440
b1111111111111111 0
b1111111111111111 :
b1111111111111111 B
1(
1%
b0 3
b0 4
b0 6
b0 ;
b0 @
b1000010000000000 <
b101 >
b1 2
b1 =
0"
#450
0-
0*
b10000110100100001000101010000110100101100110010 P
b1001 O
1"
#460
0"
#470
b1010010010111110101001101001000010010010100011001010100 P
1'
1)
b101 O
1"
#480
0%
b10 3
b10 4
b10 6
b10 ;
b10 @
b100001000000000000 <
b1111111111111101 0
b1111111111111101 :
b1111111111111101 B
b101 /
b101 5
b101 ?
b101 A
b10 &
b10 7
b10 8
0"
#490
0'
0)
b10000110100100001000101010000110100101100110001 P
b110 O
1"
#500
0"
#510
b10100100101111100110000 P
1.
b1000 O
1"
#520
b1001 >
b10 2
b10 =
0"
#530
0.
b10000110100100001000101010000110100101100110010 P
b1001 O
1"
#540
0"
#550
b1010010010111110101001101001000010010010100011001010100 P
1'
1)
b101 O
1"
#560
b1000 3
b1000 4
b1000 6
b1000 ;
b1000 @
b10000100000000000000 <
b1111111111111111 0
b1111111111111111 :
b1111111111111111 B
b1001 /
b1001 5
b1001 ?
b1001 A
b1 &
b1 7
b1 8
0"
#570
0'
0)
b10000110100100001000101010000110100101100110001 P
b110 O
1"
#580
0"
#590
b10100100101111100110000 P
1.
b1000 O
1"
#600
b10001 >
b100 2
b100 =
0"
#610
0.
b10000110100100001000101010000110100101100110010 P
b1001 O
1"
#620
0"
#630
b1010010010111110101001101001000010010010100011001010100 P
1'
1)
b101 O
1"
#640
0(
b100001 3
b100001 4
b100001 6
b100001 ;
b100001 @
1,
b1000010000000000000000 <
b10000 0
b10000 :
b10000 B
b10001 /
b10001 5
b10001 ?
b10001 A
b0 &
b0 7
b0 8
0"
#650
0'
0)
b10000110100100001000101010000110100101100110001 P
b110 O
1"
#660
0"
#670
b10100100101111100110001010111110101010101010000010001000100000101010100010001010101111101000001 P
1-
1*
b111 O
1"
#680
b1111111111111111 0
b1111111111111111 :
b1111111111111111 B
1(
b10000 3
b10000 4
b10000 6
b10000 ;
b10000 @
b100000000000000000000 <
b100101 >
b1001 2
b1001 =
0"
#690
0-
0*
b10000110100100001000101010000110100101100110010 P
b1001 O
1"
#700
0"
#710
b10001010100111001000100 P
11
b1010 O
1"
#720
0"
#730
b1 N
1"
#740
0"
#750
b10 N
1"
#760
0"
#770
b11 N
1"
#780
0"
#790
b100 N
1"
#800
0"
#810
b101 N
1"
#820
0"
#830
b110 N
1"
#840
0"
#850
b111 N
1"
#860
0"
#870
b1000 N
1"
#880
0"
#890
b1001 N
1"
#900
0"
#910
b1010 N
1"
#920
0"
#930
b1011 N
1"
#940
0"
#950
b1100 N
1"
#960
0"
#970
b1101 N
1"
#980
0"
#990
b1110 N
1"
#1000
0"
#1010
b1111 N
1"
#1020
0"
#1030
b10000 N
1"
#1040
0"
#1050
b10001 N
1"
#1060
0"
#1070
b10010 N
1"
#1080
0"
#1090
b10011 N
1"
#1100
0"
#1110
b10100 N
1"
#1120
0"
#1130
b10101 N
1"
#1140
0"
#1150
b10110 N
1"
#1160
0"
#1170
b10111 N
1"
#1180
0"
#1190
b11000 N
1"
